{
    "id": "2018-09-25T12:22:06.160921",
    "object.record.created": "2018-09-25T12:22:06.160921",
    "object.record.updated": "2018-09-25T12:25:07.110636",
    "object.type": "Book",
    "object.title": "From the Australian Front  Xmas 1917",
    "object.size": "A4",
    "object.description": " paperback, 130 pp, pictorial",
    "object.keywords": "WW1, France",
    "object.maker.name": "Cassand Company Ltdell ",
    "object.manufacture.location": "Melbourne",
    "object.manufacture.date": "1917",
    "condition.status": "fair",
    "storage.location": "ajd-library"
}